{
  "rows_used": 33365,
  "svm_max_train_samples": 6000,
  "classification": {
    "logistic_regression": {
      "best_params": {
        "clf__C": 1.0
      },
      "accuracy": 0.7758,
      "precision": 0.7647,
      "recall": 0.7779,
      "f1": 0.7713,
      "roc_auc": 0.8784,
      "train_samples": 26692
    },
    "random_forest": {
      "best_params": {
        "clf__max_depth": 20,
        "clf__min_samples_leaf": 1
      },
      "accuracy": 0.9009,
      "precision": 0.8924,
      "recall": 0.9053,
      "f1": 0.8988,
      "roc_auc": 0.9695,
      "train_samples": 26692
    },
    "svm_rbf": {
      "best_params": {
        "clf__C": 1.0,
        "clf__gamma": "scale"
      },
      "accuracy": 0.785,
      "precision": 0.7646,
      "recall": 0.8054,
      "f1": 0.7844,
      "roc_auc": 0.8806,
      "train_samples": 6000
    },
    "knn": {
      "best_params": {
        "clf__n_neighbors": 5
      },
      "accuracy": 0.8656,
      "precision": 0.8567,
      "recall": 0.8686,
      "f1": 0.8626,
      "roc_auc": 0.938,
      "train_samples": 26692
    },
    "best_model": "random_forest"
  },
  "regression": {
    "linear_regression": {
      "best_params": {},
      "mae": 4794.18,
      "rmse": 6943.99,
      "r2": 0.689
    },
    "random_forest_regressor": {
      "best_params": {
        "reg__max_depth": 20,
        "reg__min_samples_leaf": 1
      },
      "mae": 3439.94,
      "rmse": 5744.41,
      "r2": 0.7872
    },
    "best_model": "random_forest_regressor"
  }
}